express_env/__init__.py
express_env/ast.py
express_env/cli.py
express_env/commands/__init__.py
express_env/commands/generate.py
express_env/config.py
express_env/plugins/__init__.py
express_env/plugins/base.py
express_env/plugins/const.py
express_env/plugins/one_password.py
express_env/plugins/vault.py
express_env/py.typed
express_env/render.py
express_env/terminal.py
express_env/types.py
express_env-0.0.2.dist-info/LICENSE
express_env-0.0.2.dist-info/METADATA
express_env-0.0.2.dist-info/WHEEL
express_env-0.0.2.dist-info/entry_points.txt
express_env-0.0.2.dist-info/RECORD
