Metadata-Version: 2.1
Name: express-env
Version: 0.0.2
Summary: Safe and easy environment variables management
License: MIT
Author: Damian Świstowski
Author-email: damian@swistowski.org
Requires-Python: >=3.11,<4.0
Classifier: Development Status :: 2 - Pre-Alpha
Classifier: Intended Audience :: Developers
Classifier: License :: OSI Approved :: MIT License
Classifier: Natural Language :: English
Classifier: Programming Language :: Python :: 3
Classifier: Programming Language :: Python :: 3.11
Requires-Dist: pyyaml (>=6.0,<7.0)
